fyodorov_llm_agents/__init__.py
fyodorov_llm_agents/base_model.py
fyodorov_llm_agents/base_service.py
fyodorov_llm_agents/py.typed
fyodorov_llm_agents/agents/agent_executor.py
fyodorov_llm_agents/agents/agent_model.py
fyodorov_llm_agents/agents/agent_service.py
fyodorov_llm_agents/agents/openai.py
fyodorov_llm_agents/instances/instance_model.py
fyodorov_llm_agents/instances/instance_service.py
fyodorov_llm_agents/models/llm_model.py
fyodorov_llm_agents/models/llm_service.py
fyodorov_llm_agents/providers/provider_model.py
fyodorov_llm_agents/providers/provider_service.py
fyodorov_llm_agents/tools/mcp_tool_model.py
fyodorov_llm_agents/tools/mcp_tool_service.py
fyodorov_llm_agents/tools/tool.py
fyodorov_llm_agents-0.5.53.dist-info/METADATA
fyodorov_llm_agents-0.5.53.dist-info/WHEEL
fyodorov_llm_agents-0.5.53.dist-info/top_level.txt
fyodorov_llm_agents-0.5.53.dist-info/RECORD
