Metadata-Version: 2.4
Name: fyodorov_llm_agents
Version: 0.5.53
Summary: LLM agents for the Fyodorov AI suite
Author-email: Daniel Ransom <02masseur.alibis@icloud.com>
Project-URL: Homepage, https://github.com/FyodorovAI/fyodorov-llm-agents
Project-URL: Issues, https://github.com/FyodorovAI/fyodorov-llm-agents/issues
Classifier: Programming Language :: Python :: 3
Classifier: License :: OSI Approved :: MIT License
Classifier: Operating System :: OS Independent
Requires-Python: >=3.8
